{
    "Addresses": [
        {
            "Active": true,
            "ByteOrder": -1,
            "DataType": 2,
            "Factor": 0,
            "Ident": "SunSpecModel",
            "Length": 0,
            "Name": "[40192] Sunspec Model 'Status'",
            "Profile": "",
            "ReadAddress": 40191,
            "ReadFunctionCode": 3,
            "Translation": [],
            "WriteAddress": 0,
            "WriteFunctionCode": 0
        },
        {
            "Active": true,
            "ByteOrder": -1,
            "DataType": 2,
            "Factor": 0,
            "Ident": "40194_PVConn",
            "Length": 0,
            "Name": "[40194] PV Inverter Status (bitfield)",
            "Profile": "Fronius.PvInverterStatus",
            "ReadAddress": 40193,
            "ReadFunctionCode": 3,
            "Translation": [],
            "WriteAddress": 0,
            "WriteFunctionCode": 0
        },
        {
            "Active": true,
            "ByteOrder": -1,
            "DataType": 2,
            "Factor": 0,
            "Ident": "40195_StorConn",
            "Length": 0,
            "Name": "[40195] Storage Inverter Status (bitfield)",
            "Profile": "Fronius.StorageInverterStatus",
            "ReadAddress": 40194,
            "ReadFunctionCode": 3,
            "Translation": [],
            "WriteAddress": 0,
            "WriteFunctionCode": 0
        },
        {
            "Active": true,
            "ByteOrder": -1,
            "DataType": 2,
            "Factor": 0,
            "Ident": "40196_ECPConn",
            "Length": 0,
            "Name": "[40196] ECP connection status (bitfield)",
            "Profile": "Fronius.ECPConnectionStatus",
            "ReadAddress": 40195,
            "ReadFunctionCode": 3,
            "Translation": [],
            "WriteAddress": 0,
            "WriteFunctionCode": 0
        },
        {
            "Active": true,
            "ByteOrder": -1,
            "DataType": 11,
            "Factor": 0.001,
            "Ident": "40197_ActWh",
            "Length": 0,
            "Name": "[40197] AC Lifetime Active Energy",
            "Profile": "~Electricity",
            "ReadAddress": 40196,
            "ReadFunctionCode": 3,
            "Translation": [],
            "WriteAddress": 0,
            "WriteFunctionCode": 0
        },
        {
            "Active": true,
            "ByteOrder": -1,
            "DataType": 3,
            "Factor": 0,
            "Ident": "40227_StActCtl",
            "Length": 0,
            "Name": "[40227] Activ Inverter Controls (bitfield)",
            "Profile": "Fronius.InverterControls",
            "ReadAddress": 40226,
            "ReadFunctionCode": 3,
            "Translation": [],
            "WriteAddress": 0,
            "WriteFunctionCode": 0
        },
        {
            "Active": true,
            "ByteOrder": -1,
            "DataType": 10,
            "Factor": 0,
            "Ident": "40229_TmSrc",
            "Length": 4,
            "Name": "[40229] Time synchronization",
            "Profile": "",
            "ReadAddress": 40228,
            "ReadFunctionCode": 3,
            "Translation": [],
            "WriteAddress": 0,
            "WriteFunctionCode": 0
        },
        {
            "Active": true,
            "ByteOrder": -1,
            "DataType": 3,
            "Factor": 0,
            "Ident": "40233_Tms",
            "Length": 0,
            "Name": "[40233] Seconds since 01-01-2000 00:00 UTC",
            "Profile": "",
            "ReadAddress": 40232,
            "ReadFunctionCode": 3,
            "Translation": [],
            "WriteAddress": 0,
            "WriteFunctionCode": 0
        },
        {
            "Active": true,
            "ByteOrder": -1,
            "DataType": 2,
            "Factor": 0,
            "Ident": "40236_Ris",
            "Length": 0,
            "Name": "[40236] Isolation resistance",
            "Profile": "",
            "ReadAddress": 40235,
            "ReadFunctionCode": 3,
            "Translation": [],
            "WriteAddress": 0,
            "WriteFunctionCode": 0
        },
        {
            "Active": true,
            "ByteOrder": -1,
            "DataType": 2,
            "Factor": 0,
            "Ident": "40237_Ris_SF",
            "Length": 0,
            "Name": "[40237] Isolation Resistance_SF",
            "Profile": "Fronius.ScaleFactor",
            "ReadAddress": 40236,
            "ReadFunctionCode": 3,
            "Translation": [],
            "WriteAddress": 0,
            "WriteFunctionCode": 0
        }
    ],
    "ByteOrder": 0,
    "Profiles": {
        "Fronius.ECPConnectionStatus": {
            "Associations": [
                {
                    "Color": -1,
                    "Icon": "",
                    "Name": "disconnected",
                    "Value": 0.0
                },
                {
                    "Color": -1,
                    "Icon": "",
                    "Name": "connected",
                    "Value": 1.0
                },
                {
                    "Color": -1,
                    "Icon": "",
                    "Name": "[%d]",
                    "Value": 2.0
                }
            ],
            "Digits": 0,
            "Icon": "",
            "MaxValue": 1.0,
            "MinValue": 0.0,
            "Prefix": "",
            "StepSize": 1.0,
            "Suffix": "",
            "Type": 1
        },
        "Fronius.InverterControls": {
            "Associations": [
                {
                    "Color": -1,
                    "Icon": "",
                    "Name": "[%d] - No Control Active",
                    "Value": 0.0
                },
                {
                    "Color": -1,
                    "Icon": "",
                    "Name": "[%d] - WixedW",
                    "Value": 1.0
                },
                {
                    "Color": -1,
                    "Icon": "",
                    "Name": "[%d] - FixedVAR",
                    "Value": 2.0
                },
                {
                    "Color": -1,
                    "Icon": "",
                    "Name": "[%d] - FixedW & FixedVAR",
                    "Value": 3.0
                },
                {
                    "Color": -1,
                    "Icon": "",
                    "Name": "[%d] - FixedPF",
                    "Value": 4.0
                },
                {
                    "Color": -1,
                    "Icon": "",
                    "Name": "[%d] - FixedW & FixedPF",
                    "Value": 5.0
                },
                {
                    "Color": -1,
                    "Icon": "",
                    "Name": "[%d] - FixedVAR & FixedPF",
                    "Value": 6.0
                },
                {
                    "Color": -1,
                    "Icon": "",
                    "Name": "[%d] - FixedW & FixedVAR & FixedPF",
                    "Value": 7.0
                }
            ],
            "Digits": 0,
            "Icon": "",
            "MaxValue": 7.0,
            "MinValue": 0.0,
            "Prefix": "",
            "StepSize": 1.0,
            "Suffix": "",
            "Type": 1
        },
        "Fronius.PvInverterStatus": {
            "Associations": [
                {
                    "Color": -1,
                    "Icon": "",
                    "Name": "[%d] n.a.",
                    "Value": 0.0
                },
                {
                    "Color": -1,
                    "Icon": "",
                    "Name": "[%d] Connected",
                    "Value": 1.0
                },
                {
                    "Color": -1,
                    "Icon": "",
                    "Name": "[%d] Available",
                    "Value": 2.0
                },
                {
                    "Color": -1,
                    "Icon": "",
                    "Name": "[%d] Connected | Available",
                    "Value": 3.0
                },
                {
                    "Color": -1,
                    "Icon": "",
                    "Name": "[%d] Operating",
                    "Value": 4.0
                },
                {
                    "Color": -1,
                    "Icon": "",
                    "Name": "[%d] Connected | Available",
                    "Value": 5.0
                },
                {
                    "Color": -1,
                    "Icon": "",
                    "Name": "[%d] Available | Operating",
                    "Value": 6.0
                },
                {
                    "Color": -1,
                    "Icon": "",
                    "Name": "[%d] Connected | Available | Operating",
                    "Value": 7.0
                }
            ],
            "Digits": 0,
            "Icon": "",
            "MaxValue": 7.0,
            "MinValue": 0.0,
            "Prefix": "",
            "StepSize": 1.0,
            "Suffix": "",
            "Type": 1
        },
        "Fronius.ScaleFactor": {
            "Associations": [
                {
                    "Color": -1,
                    "Icon": "",
                    "Name": "10^ %d",
                    "Value": -32760.0
                },
                {
                    "Color": -1,
                    "Icon": "",
                    "Name": "10^ %d",
                    "Value": 32767.0
                },
                {
                    "Color": -1,
                    "Icon": "",
                    "Name": "n.a.",
                    "Value": 32768.0
                }
            ],
            "Digits": 0,
            "Icon": "",
            "MaxValue": 10.0,
            "MinValue": -10.0,
            "Prefix": "",
            "StepSize": 1.0,
            "Suffix": "",
            "Type": 1
        },
        "Fronius.StorageInverterStatus": {
            "Associations": [
                {
                    "Color": -1,
                    "Icon": "",
                    "Name": "[%d] n.a.",
                    "Value": 0.0
                },
                {
                    "Color": -1,
                    "Icon": "",
                    "Name": "[%d] Connected",
                    "Value": 1.0
                },
                {
                    "Color": -1,
                    "Icon": "",
                    "Name": "[%d] Available",
                    "Value": 2.0
                },
                {
                    "Color": -1,
                    "Icon": "",
                    "Name": "[%d] Connected | Available",
                    "Value": 3.0
                },
                {
                    "Color": -1,
                    "Icon": "",
                    "Name": "[%d] Operating",
                    "Value": 4.0
                },
                {
                    "Color": -1,
                    "Icon": "",
                    "Name": "[%d] Connected | Operating",
                    "Value": 5.0
                },
                {
                    "Color": -1,
                    "Icon": "",
                    "Name": "[%d] Available | Operating",
                    "Value": 6.0
                },
                {
                    "Color": -1,
                    "Icon": "",
                    "Name": "[%d] Connected | Available | Operating",
                    "Value": 7.0
                }
            ],
            "Digits": 0,
            "Icon": "",
            "MaxValue": 7.0,
            "MinValue": 0.0,
            "Prefix": "",
            "StepSize": 1.0,
            "Suffix": "",
            "Type": 1
        }
    },
    "Requests": {
        "Interval": 5000
    },
    "VirtualAddresses": [
        {
            "Active": true,
            "Ident": "VA_UpdateCnt",
            "Name": "Update Cnt",
            "Profile": "",
            "ReadAction": "$varId = @IPS_GetObjectIDByIdent(\"VA_UpdateCnt\", $_IPS['TARGET']);\r\nif ($varId === false) { return -1; } else { return GetValueInteger($varId)+1; }",
            "Translation": [],
            "VariableType": 1,
            "WriteAction": ""
        },
        {
            "Active": true,
            "Ident": "VA_LastUpdate",
            "Name": "Last Update",
            "Profile": "~UnixTimestamp",
            "ReadAction": "if(false) {\r\n    $ipsTarget = $_IPS['TARGET'];\r\n    $logSender = sprintf(\"[%s] %s\", $ipsTarget, IPS_GetName($ipsTarget));\r\n    $logMsg = sprintf(\"Fronius Modbus SunSpecModel '%s' updated\", $VALUES[\"SunSpecModel\"]);\r\n    IPS_LogMessage($logSender, $logMsg);\r\n}\r\nreturn (time());",
            "Translation": [],
            "VariableType": 1,
            "WriteAction": ""
        }
    ]
}